README.rst
setup.py
jsonrpctool/__init__.py
jsonrpctool/main.py
jsonrpctool.egg-info/PKG-INFO
jsonrpctool.egg-info/SOURCES.txt
jsonrpctool.egg-info/dependency_links.txt
jsonrpctool.egg-info/entry_points.txt
jsonrpctool.egg-info/requires.txt
jsonrpctool.egg-info/top_level.txt
jsonrpctool/tests/__init__.py