Metadata-Version: 1.0
Name: jsonrpctool
Version: 0.1.1
Summary: Commandline JSON-RPC client tool.
Home-page: https://github.com/nejucomo/jsonrpctool
Author: Nathan Wilcox
Author-email: nejucomo+dev@gmail.com
License: GPLv3
Platform: UNKNOWN
